qspd/__init__.py
qspd/data_collection.py
qspd/json_encoding.py
qspd/steps.py
qspd/util.py
qspd/tests/__init__.py
qspd/tests/test_steps.py
qspd/visualization/__init__.py
qspd/visualization/plot_angles.py
qspd/visualization/plot_angles_color.py
qspd/visualization/plot_time.py
qspd-1.0.1.dist-info/LICENSE
qspd-1.0.1.dist-info/METADATA
qspd-1.0.1.dist-info/WHEEL
qspd-1.0.1.dist-info/top_level.txt
qspd-1.0.1.dist-info/RECORD
