Metadata-Version: 2.1
Name: qspd
Version: 1.0.1
Summary: Quantum Signal Processing Decomposition
Home-page: https://gitlab.umiacs.umd.edu/amchilds/qspd
Author: Andrew Childs
Author-email: amchilds@umd.edu
License: UNKNOWN
Platform: UNKNOWN
Classifier: Programming Language :: Python :: 3
Classifier: License :: OSI Approved :: Apache Software License
Classifier: Operating System :: OS Independent
Requires-Dist: mpmath
Requires-Dist: sympy
Requires-Dist: numpy
Requires-Dist: matplotlib
